streamlit_avatar/__init__.py
streamlit_avatar/frontend/build/asset-manifest.json
streamlit_avatar/frontend/build/bootstrap.min.css
streamlit_avatar/frontend/build/index.html
streamlit_avatar/frontend/build/static/js/main.40f2a222.js
streamlit_avatar/frontend/build/static/js/main.40f2a222.js.LICENSE.txt
streamlit_avatar/frontend/build/static/js/main.40f2a222.js.map
streamlit_avatar/frontend/build/static/js/main.f4b71242.js
streamlit_avatar/frontend/build/static/js/main.f4b71242.js.LICENSE.txt
streamlit_avatar/frontend/build/static/js/main.f4b71242.js.map
streamlit_avatar-0.1.3.dist-info/LICENSE
streamlit_avatar-0.1.3.dist-info/METADATA
streamlit_avatar-0.1.3.dist-info/WHEEL
streamlit_avatar-0.1.3.dist-info/top_level.txt
streamlit_avatar-0.1.3.dist-info/RECORD
