Metadata-Version: 2.1
Name: streamlit-avatar
Version: 0.1.3
Summary: Component to display avatar icon in Streamlit
Home-page: https://github.com/ppspps824/streamlit_avatar
Author: papasim824
Author-email: papasim824@gmail.com
Requires-Python: >=3.7
License-File: LICENSE
Requires-Dist: streamlit>=0.63
Provides-Extra: devel
Requires-Dist: wheel; extra == "devel"
